Workbook

Sheet Cover
B2: CAPITALIPLY GROUP — DUE DILIGENCE MODEL
B3: Acquisition + Lender Risk + Investor Equity Analysis
B4: Prepared: 31 May 2026
B6: WORKBOOK TABS
B7: 1. Assumptions | C7: Master assumption set — FX, rates, multiples, scenarios
B8: 2. Capitaliply P&L | C8: 2025 Actual vs Q1 2026 annualized + per-app revenue trend
B9: 3. Target P&L | C9: Target company financials, Shopify fee scenario
B10: 4. Debt Stack | C10: All existing + new debt; monthly schedule; covenants
B11: 5. Sources & Uses | C11: $2.4M deal funding plan + investor cash-in
B12: 6. DSCR & Leverage | C12: Debt service coverage Base/Stress; leverage ratios
B13: 7. Valuation FF | C13: Target valuation football field (comps + DCF)
B14: 8. Cap Table | C14: Investor equity scenarios for $500K cash-in
B15: 9. Risks Matrix | C15: Risk register for creditor — severity × likelihood
B18: HEADLINE METRICS
B19: Deal price (target acquisition) | C19: 2400000
B20: of which: new debt | C20: 2000000
B21: of which: equity investor cash-in | C21: 400000
B22: Investor total cash-in (incl. WC) | C22: 500000
B24: Combined EBITDA (Capitaliply + Target FCF) | C24: ='2. Capitaliply P&L'!C16 + '3. Target P&L'!C9 -> 680541.43
B25: Total debt post-deal | C25: ='4. Debt Stack'!E27 -> 3131240.2
B26: Debt / EBITDA | C26: =C25/C24 -> 4.6011015

Sheet 1. Assumptions
A1: MASTER ASSUMPTIONS — change BLUE cells to flex scenarios
B3: FX RATES
B4: EUR/USD | C4: 1.08 | E4: Source: ECB indicative May 2026
B6: DEAL STRUCTURE
B7: Target purchase price | C7: 2400000 | E7: Per user — $2.4M total
B8: New debt raised | C8: 2000000 | E8: 12% rate, NewCo borrower, Capitaliply guarantor
B9: Equity from investor (cash-in) | C9: 500000 | E9: $400K to gap + $100K WC
B10: Deal gap (acquisition) | C10: =C7-C8 -> 400000 | E10: Auto-calc: purchase - debt
B12: DEBT TERMS — NEW DEBT
B13: Interest rate | C13: 0.12 | E13: Per user — 12% senior secured
B14: Tenor (years) | C14: 7 | E14: Sensitize 5/7/10 years
B15: Amort type | C15: Interest-only first 2y then amort | E15: Scenario flag
B17: VALUATION MULTIPLES (Shopify SaaS apps, sub-$1M ARR)
B18: Method | C18: Low | D18: High | E18: Source / commentary
B19: EV / Net Revenue | C19: 2 | D19: 4 | E19: Acquire.com Shopify deals 2024-2025 (sub-$1M ARR)
B20: EV / Gross Revenue | C20: 1.5 | D20: 3 | E20: FE International Shopify app comps
B21: EV / FCF (~EBITDA) | C21: 3 | D21: 5 | E21: TinySeed / Microacquire data
B22: EV / EBITDA (consol) | C22: 4 | D22: 6 | E22: Roll-up Shopify portfolios trade 4-6x
B25: DCF ASSUMPTIONS
B26: WACC | C26: 0.14 | E26: Small Shopify SaaS, β=1.3, Rf=4.5%, ERP=5.5%, +size premium
B27: Terminal growth | C27: 0 | E27: Conservative — portfolio organic is declining
B28: Explicit period (yrs) | C28: 5
B29: Shopify 15% fee — Base scenario | C29: 0 | E29: 0 = not enforced; 1 = enforced from Y2
B30: Shopify 15% fee — Stress scenario | C30: 1 | E30: Risk case: Shopify enforces
B33: OPERATING ASSUMPTIONS
B34: Existing portfolio organic growth | C34: -0.05 | E34: Per app trend YoY (declining 2-8%)
B35: Target organic growth | C35: 0 | E35: Conservative — assume flat
B36: Shopify revenue share (target & portfolio) | C36: 0.15 | E36: If Shopify enforces 15% on these apps

Sheet 2. Capitaliply P&L
A1: CAPITALIPLY GROUP — CONSOLIDATED P&L
C3: FY 2025 | D3: Q1 2026 | E3: 2026E (annualized) | F3: YoY
B4: Revenue | C4: 790145.93 | D4: 315055.4 | E4: =D4*4 -> 1260221.6 | F4: =IFERROR(E4/C4-1,"-") -> 0.5949226
B5: Cost of Revenue | C5: 452865.62 | D5: 201959.55 | E5: =D5*4 -> 807838.2 | F5: =IFERROR(E5/C5-1,"-") -> 0.78383645
B6: Operating Income | C6: 337280.31 | D6: 113095.85 | E6: =D6*4 -> 452383.4 | F6: =IFERROR(E6/C6-1,"-") -> 0.34126834
B8: General Business Expenses | C8: 117697.48 | D8: 31690.29 | E8: =D8*4 -> 126761.16 | F8: =IFERROR(E8/C8-1,"-") -> 0.077008276
B9: Income Before Tax | C9: 219582.83 | D9: 81405.56 | E9: =D9*4 -> 325622.24 | F9: =IFERROR(E9/C9-1,"-") -> 0.48291303
B11: Amortization (add-back) | C11: 13211.02 | D11: 13025.98 | E11: =D11*4 -> 52103.92 | F11: =IFERROR(E11/C11-1,"-") -> 2.943974
B12: Interest paid (add-back) | C12: 20342.64 | D12: 7273.97 | E12: =D12*4 -> 29095.88 | F12: =IFERROR(E12/C12-1,"-") -> 0.43029027
B13: EBITDA | C13: 253136.49 | D13: 101705.51 | E13: =D13*4 -> 406822.04 | F13: =IFERROR(E13/C13-1,"-") -> 0.60712523
B15: MARGIN ANALYSIS
B16: Gross margin | C16: =C6/C4 -> 0.42685825 | D16: =D6/D4 -> 0.35897131 | E16: =E6/E4 -> 0.35897131
B17: EBITDA margin | C17: =C13/C4 -> 0.32036676 | D17: =D13/D4 -> 0.32281786 | E17: =E13/E4 -> 0.32281786
B20: PER-APP REVENUE (annualized)
B21: App | C21: 2025 ARR | D21: 2026 ARR | E21: YoY | F21: Note
B22: MBC Bundle | C22: 423826.69 | D22: 394851.16 | E22: =IFERROR(D22/C22-1,"-") -> -0.068366459 | F22: Largest app, -7%
B23: Cartly | C23: 100832.84 | D23: 98452.14 | E23: =IFERROR(D23/C23-1,"-") -> -0.023610363 | F23: Stable -2%
B24: SLOT | C24: 37585.8 | D24: 34750.68 | E24: =IFERROR(D24/C24-1,"-") -> -0.075430615 | F24: Small, declining
B25: RecurrinGo | C25: 167894.33 | D25: 153795.99 | E25: =IFERROR(D25/C25-1,"-") -> -0.083971508 | F25: -8% YoY
B26: Split Payments | C26: 185938.02 | D26: 184888.8 | E26: =IFERROR(D26/C26-1,"-") -> -0.0056428481 | F26: Flat
B27: UpChargeFees | C27: 295234.87 | D27: 410985.9 | E27: =IFERROR(D27/C27-1,"-") -> 0.39206422 | F27: Acquired late 2025 — growth driver
B28: TOTAL portfolio (ARR) | C28: =SUM(C22:C27) -> 1211312.6 | D28: =SUM(D22:D27) -> 1277724.7 | E28: =IFERROR(D28/C28-1,"-") -> 0.054826576
B29: ORGANIC (ex-UpChargeFees) | C29: =C28-C27 -> 916077.68 | D29: =D28-D27 -> 866738.77 | E29: =IFERROR(D29/C29-1,"-") -> -0.053858871 | F29: ⚠ ORGANIC PORTFOLIO IS DECLINING

Sheet 3. Target P&L
A1: TARGET COMPANY — P&L (LTM as presented by seller)
C3: LTM ($) | D3: % of Gross | E3: Comment
B4: Gross Revenue | C4: 983587 | D4: =C4/$C$4 -> 1 | E4: Seller-reported
B5: Less: Shopify processing + payment fees | C5: =C6-C4 -> -177046 | D5: =C5/$C$4 -> -0.18000035 | E5: ≈18% — payment processing only (NO 15% rev share)
B6: Net Revenue (after fees) | C6: 806541 | D6: =C6/$C$4 -> 0.81999965
B7: Operating costs (implied) | C7: =C9-C6 -> -126000 | D7: =C7/$C$4 -> -0.12810255 | E7: Plug — only $126K of opex
B9: Free Cash Flow (FCF) | C9: 680541 | D9: =C9/$C$4 -> 0.69189711
B12: SHOPIFY 15% FEE SCENARIO ANALYSIS
B13: Scenario | C13: Annual hit | D13: FCF post-hit | E13: Comment
B14: Base — NOT enforced (current) | C14: 0 | D14: =C9 -> 680541 | E14: Status quo — what user described
B15: Stress — 15% on Gross applied | C15: =C4*'1. Assumptions'!C36 -> 147538.05 | D15: =C9-C15 -> 533002.95 | E15: Shopify already does this for apps >$1M ARR
B16: Mid — 15% phased in over 2 yr | C16: =C15*0.5 -> 73769.025 | D16: =C9-C16 -> 606771.97
B19: TARGET KEY RATIOS
B20: FCF margin (of Gross) | C20: =C9/C4 -> 0.69189711
B21: FCF margin (of Net) | C21: =C9/C6 -> 0.84377732
B22: Take rate (fees % of Gross) | C22: =1-C6/C4 -> 0.18000035

Sheet 4. Debt Stack
A1: DEBT STACK — Existing + New
B3: Name | C3: Cur | D3: Principal | E3: USD-equiv | F3: Rate | G3: Annual int. | H3: Comment
B4: CPTN DEBTS
B5: Andrey Lychkouski | C5: USD | D5: 200000 | E5: =IF(C5="EUR",D5*'1. Assumptions'!$C$4,D5) -> 200000 | F5: 0.15 | G5: =E5*F5 -> 30000 | H5: Due 25.12.2026 — penalty risk if no rollover
B6: AG-Operations | C6: USD | D6: 928 | E6: =IF(C6="EUR",D6*'1. Assumptions'!$C$4,D6) -> 928 | F6: 0.08 | G6: =E6*F6 -> 74.24 | H6: Closing next month
B7: Yuri Lavkov (Cash) | C7: EUR | D7: 33284 | E7: =IF(C7="EUR",D7*'1. Assumptions'!$C$4,D7) -> 35946.72 | F7: 0.12 | G7: =E7*F7 -> 4313.6064 | H7: INFORMAL — crypto repayment — legal risk
B8: Yuri Lavkov (CPTN) | C8: EUR | D8: 54155 | E8: =IF(C8="EUR",D8*'1. Assumptions'!$C$4,D8) -> 58487.4 | F8: 0.15 | G8: =E8*F8 -> 8773.11 | H8: Full repay by May 2027
B9: Vladimir Trofimenko | C9: EUR | D9: 7805 | E9: =IF(C9="EUR",D9*'1. Assumptions'!$C$4,D9) -> 8429.4 | F9: 0.06 | G9: =E9*F9 -> 505.764 | H9: Equal monthly installments
B10: CAPITALIPLY DEBTS
B11: Dmitri Filimonov | C11: USD | D11: 299905 | E11: =IF(C11="EUR",D11*'1. Assumptions'!$C$4,D11) -> 299905 | F11: 0.15 | G11: =E11*F11 -> 44985.75 | H11: Due June 2028 — largest single piece
B12: Tomashevich (Split) | C12: USD | D12: 15748 | E12: =IF(C12="EUR",D12*'1. Assumptions'!$C$4,D12) -> 15748 | F12: 0 | G12: =E12*F12 -> 0 | H12: Repaid w/ equity buyout
B13: Yan Stayetski | C13: USD | D13: 100000 | E13: =IF(C13="EUR",D13*'1. Assumptions'!$C$4,D13) -> 100000 | F13: 0.05 | G13: =E13*F13 -> 5000 | H13: Due Oct 2028 + 3% equity kicker (UpCharge sale)
B14: Dmitri Kurilo | C14: USD | D14: 50000 | E14: =IF(C14="EUR",D14*'1. Assumptions'!$C$4,D14) -> 50000 | F14: 0.05 | G14: =E14*F14 -> 2500 | H14: Due Oct 2028 + 1.5% equity kicker
B15: MageWorx (15%) | C15: USD | D15: 100000 | E15: =IF(C15="EUR",D15*'1. Assumptions'!$C$4,D15) -> 100000 | F15: 0.15 | G15: =E15*F15 -> 15000 | H15: Due 25.12.2026 — penalty risk
B16: MageWorx Install. | C16: USD | D16: 60000 | E16: =IF(C16="EUR",D16*'1. Assumptions'!$C$4,D16) -> 60000 | F16: 0 | G16: =E16*F16 -> 0 | H16: Zero-rate, paid in installments
B17: EpsiFund | C17: USD | D17: 78063 | E17: =IF(C17="EUR",D17*'1. Assumptions'!$C$4,D17) -> 78063 | F17: 0 | G17: =E17*F17 -> 0 | H17: Takes 19.5% of UpCharge revenue every 2 weeks
B18: AG MBC Bundles | C18: USD | D18: 58384 | E18: =IF(C18="EUR",D18*'1. Assumptions'!$C$4,D18) -> 58384 | F18: 0.08 | G18: =E18*F18 -> 4670.72 | H18: Repay when possible
B19: SpurIT (Cronics) | C19: EUR | D19: 60508 | E19: =IF(C19="EUR",D19*'1. Assumptions'!$C$4,D19) -> 65348.64 | F19: 0.12 | G19: =E19*F19 -> 7841.8368 | H19: Repay when possible
B20: TOTAL EXISTING DEBT | E20: =SUMIF(C4:C19,"USD",E4:E19)+SUMIF(C4:C19,"EUR",E4:E19) -> 1131240.2 | G20: =SUM(G4:G19) -> 123665.03
B22: MageWorx Earn-Out (cash drain May-Dec 2026) | D22: 225205 | H22: Off-balance — contractual obligation
B24: NEW DEBT (TARGET ACQUISITION)
B25: Senior secured debt | C25: USD | D25: ='1. Assumptions'!C8 -> 2000000 | E25: =D25 -> 2000000 | F25: ='1. Assumptions'!C13 -> 0.12 | G25: =E25*F25 -> 240000 | H25: 12% / 7yr (per assumptions). NewCo borrower, holding guarantor
B27: TOTAL DEBT POST-DEAL | E27: =E20+E25 -> 3131240.2 | G27: =G20+G25 -> 363665.03

Sheet 5. Sources & Uses
A1: SOURCES & USES — $2.4M Acquisition
B3: SOURCES
B4: New debt (senior secured, 12%, 7yr) | C4: ='1. Assumptions'!C8 -> 2000000 | D4: =C4/C8 -> 0.83333333
B5: Equity — investor cash-in | C5: 400000 | D5: =C5/C8 -> 0.16666667 | E5: of $500K investor cash; $100K stays for WC
B6: Founder rollover / sponsor | C6: 0 | D6: =C6/C8 -> 0 | E6: Assumed 0 — confirm with sponsor
B8: TOTAL SOURCES | C8: =SUM(C4:C7) -> 2400000 | D8: =SUM(D4:D7) -> 1
B11: USES
B12: Purchase price (target) | C12: ='1. Assumptions'!C7 -> 2400000 | D12: =C12/C16 -> 1
B13: Deal fees (legal, advisory, ~3%) | C13: =C12*0.03 -> 72000 | D13: =C13/C16 -> 0.03
B14: Working capital reserve | C14: 100000 | D14: =C14/C16 -> 0.041666667
B15: Plug / cash to balance sheet | C15: =C8-C12-C13-C14 -> -172000 | D15: =C15/C16 -> -0.071666667 | E15: If negative, sources do not cover uses
B16: TOTAL USES | C16: =SUM(C12:C15) -> 2400000 | D16: =SUM(D12:D15) -> 1
B18: BALANCE CHECK | C18: =C8-C16 -> 0 | E18: Must be zero or positive

Sheet 6. DSCR & Leverage
A1: DSCR & LEVERAGE ANALYSIS — Lender View
C3: Base | D3: Stress (Shopify 15%) | E3: Severe (15% + organic -10%) | F3: Comment
B4: EBITDA — Capitaliply (existing) | C4: ='2. Capitaliply P&L'!E13 -> 406822.04 | D4: =C4-'2. Capitaliply P&L'!E36*'1. Assumptions'!$C$36 -> 406822.04 | E4: =D4*0.9 -> 366139.84
B5: FCF — Target | C5: ='3. Target P&L'!C9 -> 680541 | D5: ='3. Target P&L'!D15 -> 533002.95 | E5: =D5*0.9 -> 479702.66
B6: Combined cash EBITDA | C6: =SUM(C4:C5) -> 1087363 | D6: =SUM(D4:D5) -> 939824.99 | E6: =SUM(E4:E5) -> 845842.49
B9: ANNUAL DEBT SERVICE
B10: Existing debt — annual P+I (per monthly schedule x 11.5) | C10: 672579 | D10: =C10 -> 672579 | E10: =C10 -> 672579 | F10: Includes earn-out, principal amort
B11: New debt — annual P+I | C11: =-PMT('1. Assumptions'!C13/12,'1. Assumptions'!C14*12,'1. Assumptions'!C8)*12 -> 423665.59 | D11: =C11 -> 423665.59 | E11: =C11 -> 423665.59 | F11: Auto-calc from assumptions (rate, tenor)
B12: TOTAL DEBT SERVICE | C12: =SUM(C10:C11) -> 1096244.6 | D12: =SUM(D10:D11) -> 1096244.6 | E12: =SUM(E10:E11) -> 1096244.6
B15: DEBT SERVICE COVERAGE RATIO (DSCR)
B16: DSCR (EBITDA / Debt Service) | C16: =C6/C12 -> 0.99189821 | D16: =D6/D12 -> 0.85731323 | E16: =E6/E12 -> 0.77158191 | F16: Standard covenant: ≥1.25x
B17: DSCR Covenant pass? (≥1.25x) | C17: =IF(C16>=1.25,"✓ PASS","✗ FAIL") -> ✗ FAIL | D17: =IF(D16>=1.25,"✓ PASS","✗ FAIL") -> ✗ FAIL | E17: =IF(E16>=1.25,"✓ PASS","✗ FAIL") -> ✗ FAIL
B20: LEVERAGE RATIOS
B21: Total Debt | C21: ='4. Debt Stack'!E27 -> 3131240.2 | D21: =C21 -> 3131240.2 | E21: =C21 -> 3131240.2
B22: Debt / EBITDA | C22: =C21/C6 -> 2.879664 | D22: =D21/D6 -> 3.3317269 | E22: =E21/E6 -> 3.7019187 | F22: Typical SMB ceiling: 3.5-4.0x
B23: Interest Coverage (EBITDA / Interest) | C23: =C6/('4. Debt Stack'!G27) -> 2.9900127 | D23: =D6/('4. Debt Stack'!G27) -> 2.584315 | E23: =E6/('4. Debt Stack'!G27) -> 2.3258835 | F23: Typical: ≥3x
B26: LENDER VERDICT
B27: Base scenario: | C27: =IF(C16>=1.25,"✓ Bankable","⚠ Marginal (covenant tight)") -> ⚠ Marginal (covenant tight)
B28: Stress (Shopify 15%): | C28: =IF(D16>=1.25,"✓ Bankable","✗ Does NOT cover debt service") -> ✗ Does NOT cover debt service
B29: Severe (Shopify + portfolio decline): | C29: =IF(E16>=1.25,"✓ Bankable","✗ DISTRESSED — default scenario") -> ✗ DISTRESSED — default scenario

Sheet 7. Valuation FF
A1: TARGET VALUATION — Football Field
C3: Low ($) | D3: Mid ($) | E3: High ($) | F3: Implied
B4: EV / Net Revenue (2-4x) | C4: ='3. Target P&L'!C6*'1. Assumptions'!C19 -> 1613082 | D4: ='3. Target P&L'!C6*('1. Assumptions'!C19+'1. Assumptions'!D19)/2 -> 2419623 | E4: ='3. Target P&L'!C6*'1. Assumptions'!D19 -> 3226164 | F4: On Net Revenue $806K
B5: EV / Gross Revenue (1.5-3x) | C5: ='3. Target P&L'!C4*'1. Assumptions'!C20 -> 1475380.5 | D5: ='3. Target P&L'!C4*('1. Assumptions'!C20+'1. Assumptions'!D20)/2 -> 2213070.8 | E5: ='3. Target P&L'!C4*'1. Assumptions'!D20 -> 2950761 | F5: On Gross Revenue $984K
B6: EV / FCF (3-5x) | C6: ='3. Target P&L'!C9*'1. Assumptions'!C21 -> 2041623 | D6: ='3. Target P&L'!C9*('1. Assumptions'!C21+'1. Assumptions'!D21)/2 -> 2722164 | E6: ='3. Target P&L'!C9*'1. Assumptions'!D21 -> 3402705 | F6: On FCF $681K
B7: DCF — Base (no Shopify 15%) | C7: =PV('1. Assumptions'!C26,'1. Assumptions'!C28,-'3. Target P&L'!C9,0,0)+('3. Target P&L'!C9/'1. Assumptions'!C26)/(1+'1. Assumptions'!C26)^'1. Assumptions'!C28 -> 4861007.1 | D7: =C7 -> 4861007.1 | E7: =C7*1.2 -> 5833208.6 | F7: Flat FCF, g=0%, WACC=14%
B8: DCF — Shopify 15% stress | C8: =PV('1. Assumptions'!C26,'1. Assumptions'!C28,-'3. Target P&L'!D15,0,0)+('3. Target P&L'!D15/'1. Assumptions'!C26)/(1+'1. Assumptions'!C26)^'1. Assumptions'!C28 -> 3807163.9 | D8: =C8 -> 3807163.9 | E8: =C8 -> 3807163.9 | F8: FCF cut by Shopify 15% Y2+
B11: SYNTHESIS
B12: Floor (distressed / DCF stress) | C12: =MIN(C4:C8) -> 1475380.5 | D12: =AVERAGE(C4:C6) -> 1710028.5
B13: Fair value range | C13: =AVERAGE(C4:C6) -> 1710028.5 | D13: =AVERAGE(D4:D6) -> 2451619.2 | E13: =AVERAGE(E4:E6) -> 3193210
B14: Strategic premium / Bull | C14: =D13*1.15 -> 2819362.1 | D14: =D13*1.25 -> 3064524.1 | E14: =E13*1.3 -> 4151173
B16: DEAL PRICE (per term sheet) | C16: 2000000 | D16: 2400000 | E16: 2400000 | F16: User-confirmed deal price
B17: Implied multiple (Deal / FCF) | C17: =D16/'3. Target P&L'!C9 -> 3.526606 | F17: Comp range: 3-5x → deal is fair-to-mid
B18: Implied multiple (Deal / Net Rev) | C18: =D16/'3. Target P&L'!C6 -> 2.9756702 | F18: Comp range: 2-4x → deal is mid
B20: VERDICT | C20: Deal price is REASONABLE — within fair value range

Sheet 8. Cap Table
A1: INVESTOR EQUITY — $500K Cash-In Scenarios
B3: Scenario A — Investor invests in NewCo SPV (target only, with $2M debt)
B4: Target Enterprise Value (fair, mid-comps) | C4: ='7. Valuation FF'!D13 -> 2451619.2
B5: Less: New debt at closing | C5: =-'1. Assumptions'!C8 -> -2000000
B6: NewCo equity value pre-money | C6: =C4+C5 -> 451619.25
B7: Investor cash-in | C7: 500000
B8: NewCo equity post-money | C8: =C6+C7 -> 951619.25
B9: Investor stake (Scenario A) | C9: =C7/C8 -> 0.52542022 | F9: Equity-value approach
B12: Scenario B — Investor invests in Capitaliply Holding (consolidated)
C13: 4x EBITDA | D13: 5x EBITDA | E13: 6x EBITDA
B14: Combined EBITDA (Capitaliply + Target) | C14: ='6. DSCR & Leverage'!C6 -> 1087363 | D14: =C14 -> 1087363 | E14: =C14 -> 1087363
B15: Enterprise Value (multiple x EBITDA) | C15: =C14*4 -> 4349452.2 | D15: =D14*5 -> 5436815.2 | E15: =E14*6 -> 6524178.2
B16: Less: Total combined debt | C16: =-'4. Debt Stack'!E27 -> -3131240.2 | D16: =C16 -> -3131240.2 | E16: =C16 -> -3131240.2
B17: Holding equity pre-money | C17: =C15+C16 -> 1218212 | D17: =D15+D16 -> 2305575 | E17: =E15+E16 -> 3392938.1
B18: Plus: Investor cash-in | C18: 500000 | D18: 500000 | E18: 500000
B19: Holding equity post-money | C19: =C17+C18 -> 1718212 | D19: =D17+D18 -> 2805575 | E19: =E17+E18 -> 3892938.1
B20: Investor stake (Scenario B) | C20: =C18/C19 -> 0.29100018 | D20: =D18/D19 -> 0.17821658 | E20: =E18/E19 -> 0.1284377
B23: RECOMMENDED DEAL TERMS
B24: Structure | C24: Investor takes preferred equity in NewCo SPV (acquisition vehicle)
B25: Equity stake range | C25: 25-35% (Scenario A midpoint)
B26: Liquidation preference | C26: 1x non-participating, then convert
B27: Anti-dilution | C27: Broad-based weighted average
B28: Board / info rights | C28: 1 board observer seat + monthly KPI pack
B29: Drag/tag | C29: Standard drag at 75%, tag-along at any sale
B30: Equity kicker risk | C30: Note: existing Yan + Kurilo holds 4.5% of UpCharge sale proceeds
B31: Reserved matters | C31: Approval rights on: new debt >$200K, M&A, founder comp >base

Sheet 9. Risks Matrix
A1: RISK REGISTER — Creditor Perspective
B3: # | C3: Risk | D3: Description / impact | E3: Severity | F3: Likelihood | G3: Score | H3: Mitigant required
B4: 1 | C4: Shopify 15% revenue share enforcement | D4: Apps may be brought into 15% Shopify rev-share. Combined hit ~$339K/yr — breaks DSCR. | E4: 5 | F4: 4 | G4: =E4*F4 -> 20 | H4: Pre-fund 6-month DS reserve; Shopify-fee covenant trip with cash sweep
B5: 2 | C5: DSCR < 1.25x in stress case | D5: Base DSCR ~1.0x; stress 0.6-0.8x. Insufficient cushion for typical lender covenant | E5: 5 | F5: 4 | G5: =E5*F5 -> 20 | H5: Tenor stretch to 10yr, interest-only 2yr, mandatory cash sweep above $X EBITDA
B6: 3 | C6: Organic portfolio in decline (-5.4% YoY) | D6: Every existing app down 2-8% — growth is purely from UpCharge acquisition | E6: 4 | F6: 5 | G6: =E6*F6 -> 20 | H6: Operating covenants: minimum portfolio ARR floor; product-investment commitment
B7: 4 | C7: Customer / app concentration | D7: MBC Bundle + UpChargeFees = 63% of revenue. Single app failure = 30%+ revenue loss | E7: 4 | F7: 3 | G7: =E7*F7 -> 12 | H7: App-level KPI reporting; cross-collateralization across portfolio
B8: 5 | C8: Existing debt stack is heavy + complex | D8: $1.13M existing debt + $2M new = $3.1M total / $1.1M EBITDA = 2.9x — top of SMB range. Many insider loans, informal docs | E8: 4 | F8: 4 | G8: =E8*F8 -> 16 | H8: Mandatory debt cleanup pre-close; refinance/subordinate insider debt
B9: 6 | C9: Informal / crypto-routed debt repayment | D9: Yuri Lavkov Cash (€33K) not formally documented, paid via crypto. AML/tax exposure | E9: 4 | F9: 3 | G9: =E9*F9 -> 12 | H9: Require formal documentation pre-close; tax counsel opinion
B10: 7 | C10: FX risk — EUR liabilities | D10: €155K EUR debt, USD revenue. EUR strength = larger USD service cost | E10: 2 | F10: 3 | G10: =E10*F10 -> 6 | H10: FX hedge for >12-month obligations OR convert to USD
B11: 8 | C11: Earn-out drag ($29K/month thru 2026) | D11: MageWorx earn-out absorbs $338K/yr cash through Dec 2026, then drops | E11: 3 | F11: 5 | G11: =E11*F11 -> 15 | H11: Reflected in DSCR; covenant calc should add back during step-down period
B12: 9 | C12: Equity kicker dilution (4.5% of UpCharge) | D12: Stayetski 3% + Kurilo 1.5% of UpCharge sale proceeds — reduces creditor recovery in liquidation | E12: 2 | F12: 4 | G12: =E12*F12 -> 8 | H12: Subordinate equity kickers to senior debt repayment
B13: 10 | C13: Founder-dependence | D13: Small operator team; founders also act as creditors and shareholders. Key-person risk | E13: 3 | F13: 3 | G13: =E13*F13 -> 9 | H13: Key-person life insurance; non-compete; phased payouts
B14: 11 | C14: Target seller-reported numbers (no audit) | D14: Target P&L is seller-prepared; QofE not done. Risk of revenue recognition / addback aggression | E14: 5 | F14: 3 | G14: =E14*F14 -> 15 | H14: QofE (3rd-party Quality of Earnings) MANDATORY pre-close; PPA included in deal docs
B15: 12 | C15: Holding guarantee value limited | D15: Capitaliply EBITDA only $407K standalone; cannot rescue NewCo if target underperforms | E15: 4 | F15: 3 | G15: =E15*F15 -> 12 | H15: Cross-default; cash sweep at holding; restrict distributions to shareholders
... B18: 15 | C18: Russia/CIS founder geography | D18: If founders are Russia/Belarus-resident → sanctions, banking, payment risk | E18: 4 | F18: 3 | G18: =E18*F18 -> 12 | H18: KYC, sanctions screening, structure via clean jurisdiction (Cyprus/NL)
B20: Severity: 1=trivial, 5=critical | Likelihood: 1=remote, 5=near-certain | Score = Sev × Lik (≥16 = RED, 9-15 = YELLOW)
